{"/LCK_2020_Spring_RegularSeason": {"KP": "66.7%", "K": "21", "DMG%": "8.4%", "Pos": "Support", "W%": "73%", "CSPM": "1.7", "DTH%": "20.4%", "A": "256", "CTR%": "53%", "EGPM": "116", "WPM": "1.48", "GD10": "192", "STL": "", "DPM": "158", "FB%": "33%", "KS%": "5.1%", "CSD10": "9.7", "D": "50", "KDA": "5.5", "WCPM": "0.29", "GP": "30", "CS%P15": "4.7%", "XPD10": "99", "Team": "Gen.G", "D%P15": "", "GOLD%": "10.4%"}, "/LCK_2021_Summer_Playoffs": {"KP": "76.7%", "K": "3", "DMG%": "6.0%", "Pos": "Support", "W%": "25%", "CSPM": "0.9", "DTH%": "19.4%", "A": "30", "CTR%": "0%", "EGPM": "95", "WPM": "2.26", "GD10": "191", "STL": "0", "DPM": "96", "FB%": "25%", "KS%": "7.0%", "CSD10": "-2.3", "D": "12", "KDA": "2.8", "WCPM": "0.34", "GP": "4", "CS%P15": "1.9%", "XPD10": "132", "Team": "Gen.G", "D%P15": "5.4%", "GOLD%": "8.7%"}, "/LCK_2020_Summer_RegularSeason": {"KP": "60.4%", "K": "29", "DMG%": "7.0%", "Pos": "Support", "W%": "75%", "CSPM": "0.9", "DTH%": "24.5%", "A": "310", "CTR%": "67%", "EGPM": "103", "WPM": "1.54", "GD10": "-32", "STL": "", "DPM": "141", "FB%": "25%", "KS%": "5.2%", "CSD10": "-4.9", "D": "82", "KDA": "4.1", "WCPM": "0.35", "GP": "36", "CS%P15": "2.4%", "XPD10": "-223", "Team": "Gen.G", "D%P15": "", "GOLD%": "8.4%"}, "/LCK_2021_Spring_Playoffs": {"KP": "58.2%", "K": "6", "DMG%": "5.8%", "Pos": "Support", "W%": "50%", "CSPM": "0.7", "DTH%": "20.8%", "A": "33", "CTR%": "83%", "EGPM": "84", "WPM": "1.76", "GD10": "-529", "STL": "", "DPM": "98", "FB%": "17%", "KS%": "9.0%", "CSD10": "-34.2", "D": "11", "KDA": "3.5", "WCPM": "0.23", "GP": "6", "CS%P15": "1.6%", "XPD10": "-286", "Team": "Gen.G", "D%P15": "", "GOLD%": "8.1%"}, "/LCK_2021_Spring_RegularSeason": {"KP": "60.0%", "K": "26", "DMG%": "7.2%", "Pos": "Support", "W%": "66%", "CSPM": "1.1", "DTH%": "23.9%", "A": "302", "CTR%": "57%", "EGPM": "100", "WPM": "1.74", "GD10": "-18", "STL": "", "DPM": "130", "FB%": "27%", "KS%": "4.8%", "CSD10": "-2.5", "D": "104", "KDA": "3.2", "WCPM": "0.34", "GP": "44", "CS%P15": "2.5%", "XPD10": "-38", "Team": "Gen.G", "D%P15": "", "GOLD%": "8.3%"}, "/LCK_2021_Summer_RegularSeason": {"KP": "64.3%", "K": "18", "DMG%": "5.9%", "Pos": "Support", "W%": "59%", "CSPM": "1", "DTH%": "25.7%", "A": "371", "CTR%": "46%", "EGPM": "92", "WPM": "1.69", "GD10": "-63", "STL": "0", "DPM": "108", "FB%": "30%", "KS%": "3.0%", "CSD10": "-0.4", "D": "126", "KDA": "3.1", "WCPM": "0.34", "GP": "46", "CS%P15": "2.1%", "XPD10": "-20", "Team": "Gen.G", "D%P15": "6.3%", "GOLD%": "8.1%"}, "/LCK_2020_Spring_Playoffs": {"KP": "44.4%", "K": "1", "DMG%": "11.2%", "Pos": "Support", "W%": "0%", "CSPM": "0.7", "DTH%": "20.0%", "A": "7", "CTR%": "67%", "EGPM": "63", "WPM": "1.59", "GD10": "-10", "STL": "", "DPM": "162", "FB%": "0%", "KS%": "5.6%", "CSD10": "0", "D": "9", "KDA": "0.9", "WCPM": "0.19", "GP": "3", "CS%P15": "1.5%", "XPD10": "91", "Team": "Gen.G", "D%P15": "", "GOLD%": "7.2%"}, "/LCK_2020_Summer_Playoffs": {"KP": "64.4%", "K": "9", "DMG%": "11.2%", "Pos": "Support", "W%": "63%", "CSPM": "1", "DTH%": "20.5%", "A": "94", "CTR%": "17%", "EGPM": "133", "WPM": "1.56", "GD10": "205", "STL": "", "DPM": "283", "FB%": "50%", "KS%": "5.6%", "CSD10": "-4.8", "D": "17", "KDA": "6.1", "WCPM": "0.43", "GP": "8", "CS%P15": "3.0%", "XPD10": "320", "Team": "Gen.G", "D%P15": "", "GOLD%": "10.1%"}}