{"/LCK_2017_Summer_RegularSeason": {"KP": "65.1%", "K": "14", "DMG%": "7.5%", "Pos": "Support", "W%": "29%", "CSPM": "1.2", "DTH%": "19.3%", "A": "227", "CTR%": "56%", "EGPM": "119", "WPM": "1.42", "GD10": "26", "STL": "", "DPM": "123", "FB%": "16%", "KS%": "3.8%", "CSD10": "-0.3", "D": "90", "KDA": "2.7", "WCPM": "0.36", "GP": "45", "CS%P15": "3.8%", "XPD10": "1", "Team": "bbq Olivers", "D%P15": "", "GOLD%": "11.1%"}, "/LCK_2016_Summer_RegularSeason": {"KP": "70.3%", "K": "5", "DMG%": "5.2%", "Pos": "Support", "W%": "33%", "CSPM": "1", "DTH%": "31.1%", "A": "66", "CTR%": "", "EGPM": "114", "WPM": "1.55", "GD10": "100", "STL": "", "DPM": "86", "FB%": "33%", "KS%": "5.0%", "CSD10": "2.8", "D": "41", "KDA": "1.7", "WCPM": "0.39", "GP": "12", "CS%P15": "3.8%", "XPD10": "-133", "Team": "ESC Ever", "D%P15": "", "GOLD%": "10.7%"}, "/LCK_2017_Spring_RegularSeason": {"KP": "70.5%", "K": "26", "DMG%": "11.3%", "Pos": "Support", "W%": "36%", "CSPM": "0.8", "DTH%": "18.5%", "A": "282", "CTR%": "41%", "EGPM": "123", "WPM": "1.5", "GD10": "-98", "STL": "", "DPM": "202", "FB%": "9%", "KS%": "5.9%", "CSD10": "-1.3", "D": "88", "KDA": "3.5", "WCPM": "0.42", "GP": "44", "CS%P15": "2.9%", "XPD10": "-115", "Team": "bbq Olivers", "D%P15": "", "GOLD%": "11.1%"}}