{"/LEC_2021_Summer_RegularSeason": {"KDA": "3.5", "D": "51", "DPM": "459", "Pos": "Middle", "CTR%": "44%", "W%": "67%", "GD10": "193", "KP": "61.2%", "DTH%": "23.2%", "CSD10": "4.7", "A": "110", "WPM": "0.4", "EGPM": "274", "GOLD%": "22.3%", "WCPM": "0.19", "KS%": "23.4%", "K": "68", "GP": "18", "FB%": "28%", "Team": "G2 Esports", "DMG%": "22.7%", "CSPM": "8.2", "XPD10": "136", "CS%P15": "22.4%"}, "/LEC_2021_Summer_Playoffs": {"KDA": "2.5", "D": "31", "DPM": "505", "Pos": "Middle", "CTR%": "56%", "W%": "33%", "GD10": "-112", "KP": "73.1%", "DTH%": "22.0%", "CSD10": "1.8", "A": "50", "WPM": "0.35", "EGPM": "272", "GOLD%": "24.7%", "WCPM": "0.2", "KS%": "26.9%", "K": "29", "GP": "9", "FB%": "11%", "Team": "G2 Esports", "DMG%": "25.5%", "CSPM": "8.7", "XPD10": "-2", "CS%P15": "25.8%"}, "/LEC_2020_Spring_Playoffs": {"KDA": "4.8", "D": "38", "DPM": "575", "Pos": "Middle", "CTR%": "44%", "W%": "61%", "GD10": "88", "KP": "71.3%", "DTH%": "16.2%", "CSD10": "-1.4", "A": "95", "WPM": "0.4", "EGPM": "303", "GOLD%": "26.2%", "WCPM": "0.19", "KS%": "33.9%", "K": "86", "GP": "18", "FB%": "22%", "Team": "G2 Esports", "DMG%": "29.4%", "CSPM": "9.2", "XPD10": "-71", "CS%P15": "26.8%"}, "/LEC_2020_Spring_RegularSeason": {"KDA": "3.8", "D": "57", "DPM": "747", "Pos": "ADC", "CTR%": "31%", "W%": "69%", "GD10": "-70", "KP": "74.0%", "DTH%": "22.4%", "CSD10": "-0.9", "A": "112", "WPM": "0.35", "EGPM": "334", "GOLD%": "27.9%", "WCPM": "0.28", "KS%": "36.1%", "K": "107", "GP": "16", "FB%": "31%", "Team": "G2 Esports", "DMG%": "32.9%", "CSPM": "8.8", "XPD10": "-236", "CS%P15": "30.1%"}, "/LEC_2017_Summer_Playoffs": {"KDA": "3.2", "D": "19", "DPM": "508", "Pos": "Middle", "CTR%": "", "W%": "44%", "GD10": "103", "KP": "70.6%", "DTH%": "20.7%", "CSD10": "4.2", "A": "38", "WPM": "0.49", "EGPM": "258", "GOLD%": "23.0%", "WCPM": "0.13", "KS%": "25.9%", "K": "22", "GP": "9", "FB%": "11%", "Team": "Fnatic", "DMG%": "28.2%", "CSPM": "8.9", "XPD10": "98", "CS%P15": "26.5%"}, "/LEC_2020_Summer_RegularSeason": {"KDA": "4.8", "D": "38", "DPM": "575", "Pos": "Middle", "CTR%": "44%", "W%": "61%", "GD10": "88", "KP": "71.3%", "DTH%": "16.2%", "CSD10": "-1.4", "A": "95", "WPM": "0.4", "EGPM": "303", "GOLD%": "26.2%", "WCPM": "0.19", "KS%": "33.9%", "K": "86", "GP": "18", "FB%": "22%", "Team": "G2 Esports", "DMG%": "29.4%", "CSPM": "9.2", "XPD10": "-71", "CS%P15": "26.8%"}, "/LEC_2018_Spring_Playoffs": {"KDA": "7.1", "D": "11", "DPM": "663", "Pos": "Middle", "CTR%": "29%", "W%": "86%", "GD10": "120", "KP": "80.4%", "DTH%": "18.3%", "CSD10": "2.7", "A": "47", "WPM": "0.49", "EGPM": "310", "GOLD%": "24.2%", "WCPM": "0.15", "KS%": "32.0%", "K": "31", "GP": "7", "FB%": "14%", "Team": "Fnatic", "DMG%": "29.9%", "CSPM": "9.6", "XPD10": "243", "CS%P15": "25.7%"}, "/LEC_2017_Spring_Playoffs": {"KDA": "3.6", "D": "23", "DPM": "462", "Pos": "Middle", "CTR%": "", "W%": "70%", "GD10": "-20", "KP": "54.3%", "DTH%": "28.0%", "CSD10": "-1.6", "A": "46", "WPM": "0.47", "EGPM": "284", "GOLD%": "23.1%", "WCPM": "0.16", "KS%": "23.8%", "K": "36", "GP": "10", "FB%": "10%", "Team": "Fnatic", "DMG%": "25.4%", "CSPM": "8.9", "XPD10": "2", "CS%P15": "28.0%"}, "/LEC_2019_Spring_Playoffs": {"KDA": "3.8", "D": "51", "DPM": "599", "Pos": "Middle", "CTR%": "50%", "W%": "83%", "GD10": "277", "KP": "53.6%", "DTH%": "23.8%", "CSD10": "4.1", "A": "89", "WPM": "0.36", "EGPM": "316", "GOLD%": "23.6%", "WCPM": "0.18", "KS%": "29.2%", "K": "107", "GP": "18", "FB%": "33%", "Team": "G2 Esports", "DMG%": "27.1%", "CSPM": "8.4", "XPD10": "158", "CS%P15": "25.6%"}, "/LEC_2019_Summer_Playoffs": {"KDA": "3", "D": "32", "DPM": "520", "Pos": "Middle", "CTR%": "50%", "W%": "60%", "GD10": "-39", "KP": "52.5%", "DTH%": "23.2%", "CSD10": "3.5", "A": "50", "WPM": "0.44", "EGPM": "263", "GOLD%": "21.7%", "WCPM": "0.12", "KS%": "25.1%", "K": "46", "GP": "10", "FB%": "20%", "Team": "G2 Esports", "DMG%": "25.8%", "CSPM": "7.7", "XPD10": "126", "CS%P15": "20.9%"}, "/LEC_2018_Summer_Playoffs": {"KDA": "3.8", "D": "20", "DPM": "610", "Pos": "Middle", "CTR%": "63%", "W%": "75%", "GD10": "-73", "KP": "76.8%", "DTH%": "24.1%", "CSD10": "-2.3", "A": "44", "WPM": "0.44", "EGPM": "288", "GOLD%": "25.9%", "WCPM": "0.27", "KS%": "32.3%", "K": "32", "GP": "8", "FB%": "13%", "Team": "Fnatic", "DMG%": "31.6%", "CSPM": "9", "XPD10": "-168", "CS%P15": "27.4%"}, "/LEC_2021_Spring_RegularSeason": {"KDA": "3.4", "D": "38", "DPM": "605", "Pos": "Middle", "CTR%": "54%", "W%": "38%", "GD10": "1", "KP": "80.4%", "DTH%": "18.3%", "CSD10": "-1.5", "A": "77", "WPM": "0.41", "EGPM": "296", "GOLD%": "27.5%", "WCPM": "0.18", "KS%": "33.1%", "K": "54", "GP": "13", "FB%": "15%", "Team": "G2 Esports", "DMG%": "31.7%", "CSPM": "9", "XPD10": "-57", "CS%P15": "27.7%"}, "/LEC_2020_Summer_Playoffs": {"KDA": "4.7", "D": "41", "DPM": "561", "Pos": "Middle", "CTR%": "59%", "W%": "65%", "GD10": "63", "KP": "67.8%", "DTH%": "16.7%", "CSD10": "5.6", "A": "99", "WPM": "0.37", "EGPM": "292", "GOLD%": "24.9%", "WCPM": "0.18", "KS%": "33.2%", "K": "95", "GP": "17", "FB%": "24%", "Team": "G2 Esports", "DMG%": "27.0%", "CSPM": "8.5", "XPD10": "26", "CS%P15": "25.6%"}, "/LEC_2021_Spring_Playoffs": {"KDA": "3.5", "D": "51", "DPM": "459", "Pos": "Middle", "CTR%": "44%", "W%": "67%", "GD10": "193", "KP": "61.2%", "DTH%": "23.2%", "CSD10": "4.7", "A": "110", "WPM": "0.4", "EGPM": "274", "GOLD%": "22.3%", "WCPM": "0.19", "KS%": "23.4%", "K": "68", "GP": "18", "FB%": "28%", "Team": "G2 Esports", "DMG%": "22.7%", "CSPM": "8.2", "XPD10": "136", "CS%P15": "22.4%"}, "/LEC_2018_Spring_RegularSeason": {"KDA": "7.1", "D": "11", "DPM": "663", "Pos": "Middle", "CTR%": "29%", "W%": "86%", "GD10": "120", "KP": "80.4%", "DTH%": "18.3%", "CSD10": "2.7", "A": "47", "WPM": "0.49", "EGPM": "310", "GOLD%": "24.2%", "WCPM": "0.15", "KS%": "32.0%", "K": "31", "GP": "7", "FB%": "14%", "Team": "Fnatic", "DMG%": "29.9%", "CSPM": "9.6", "XPD10": "243", "CS%P15": "25.7%"}, "/LEC_2019_Summer_RegularSeason": {"KDA": "6.6", "D": "40", "DPM": "627", "Pos": "ADC", "CTR%": "39%", "W%": "83%", "GD10": "-10", "KP": "74.3%", "DTH%": "18.2%", "CSD10": "-7.7", "A": "182", "WPM": "0.32", "EGPM": "293", "GOLD%": "24.4%", "WCPM": "0.24", "KS%": "22.9%", "K": "81", "GP": "18", "FB%": "44%", "Team": "G2 Esports", "DMG%": "27.2%", "CSPM": "8", "XPD10": "148", "CS%P15": "29.0%"}, "/LEC_2018_Summer_RegularSeason": {"KDA": "4", "D": "47", "DPM": "550", "Pos": "Middle", "CTR%": "39%", "W%": "72%", "GD10": "-27", "KP": "60.3%", "DTH%": "21.2%", "CSD10": "2.8", "A": "95", "WPM": "0.46", "EGPM": "285", "GOLD%": "22.6%", "WCPM": "0.22", "KS%": "29.7%", "K": "92", "GP": "18", "FB%": "11%", "Team": "G2 Esports", "DMG%": "25.8%", "CSPM": "8.4", "XPD10": "-72", "CS%P15": "24.0%"}, "/LEC_2019_Spring_RegularSeason": {"KDA": "17", "D": "0", "DPM": "292", "Pos": "Support", "CTR%": "100%", "W%": "100%", "GD10": "-638", "KP": "70.8%", "DTH%": "0.0%", "CSD10": "-53", "A": "11", "WPM": "0.8", "EGPM": "225", "GOLD%": "15.1%", "WCPM": "0.32", "KS%": "25.0%", "K": "6", "GP": "1", "FB%": "0%", "Team": "G2 Esports", "DMG%": "14.9%", "CSPM": "2.2", "XPD10": "-821", "CS%P15": "8.2%"}}