{"/LEC_2017_Spring_RegularSeason": {"KDA": "3.8", "D": "6", "DPM": "287", "Pos": "Jungle", "CTR%": "", "W%": "50%", "GD10": "1", "KP": "74.2%", "DTH%": "25.0%", "CSD10": "1", "A": "22", "WPM": "1.17", "EGPM": "233", "GOLD%": "18.4%", "WCPM": "0.49", "KS%": "3.2%", "K": "1", "GP": "2", "FB%": "100%", "Team": "Unicorns Of Love", "DMG%": "14.9%", "CSPM": "4.6", "XPD10": "-2", "CS%P15": "15.4%"}, "/LEC_2016_Spring_RegularSeason": {"KDA": "3.8", "D": "6", "DPM": "287", "Pos": "Jungle", "CTR%": "", "W%": "50%", "GD10": "1", "KP": "74.2%", "DTH%": "25.0%", "CSD10": "1", "A": "22", "WPM": "1.17", "EGPM": "233", "GOLD%": "18.4%", "WCPM": "0.49", "KS%": "3.2%", "K": "1", "GP": "2", "FB%": "100%", "Team": "Unicorns Of Love", "DMG%": "14.9%", "CSPM": "4.6", "XPD10": "-2", "CS%P15": "15.4%"}}