{"/LEC_2017_Spring_RegularSeason": {"KP": "81.3%", "W%": "50%", "CS%P15": "4.8%", "KDA": "2.6", "A": "13", "WCPM": "0.23", "GD10": "-77", "XPD10": "-33", "DMG%": "7.5%", "DTH%": "21.7%", "KS%": "0.0%", "GOLD%": "10.7%", "CTR%": "", "CSD10": "0", "FB%": "50%", "GP": "2", "DPM": "121", "K": "0", "Team": "Giants Gaming", "EGPM": "123", "CSPM": "1.4", "WPM": "1.12", "Pos": "Support", "D": "5"}, "/LEC_2016_Spring_RegularSeason": {"KP": "81.3%", "W%": "50%", "CS%P15": "4.8%", "KDA": "2.6", "A": "13", "WCPM": "0.23", "GD10": "-77", "XPD10": "-33", "DMG%": "7.5%", "DTH%": "21.7%", "KS%": "0.0%", "GOLD%": "10.7%", "CTR%": "", "CSD10": "0", "FB%": "50%", "GP": "2", "DPM": "121", "K": "0", "Team": "Giants Gaming", "EGPM": "123", "CSPM": "1.4", "WPM": "1.12", "Pos": "Support", "D": "5"}}