{"/LEC_2021_Summer_RegularSeason": {"KDA": "4", "D": "39", "DPM": "461", "Pos": "Top", "CTR%": "61%", "W%": "72%", "GD10": "274", "KP": "55.6%", "DTH%": "20.5%", "CSD10": "2.4", "A": "104", "WPM": "0.4", "EGPM": "253", "GOLD%": "20.4%", "WCPM": "0.22", "KS%": "18.3%", "K": "51", "GP": "18", "FB%": "22%", "Team": "Rogue", "DMG%": "23.6%", "CSPM": "7.6", "XPD10": "89", "CS%P15": "22.2%"}, "/LEC_2016_Spring_Playoffs": {"KDA": "4.3", "D": "41", "DPM": "415", "Pos": "Top", "CTR%": "", "W%": "67%", "GD10": "44", "KP": "69.7%", "DTH%": "19.9%", "CSD10": "2.8", "A": "135", "WPM": "0.41", "EGPM": "215", "GOLD%": "20.6%", "WCPM": "0.08", "KS%": "15.9%", "K": "40", "GP": "18", "FB%": "33%", "Team": "H2k-Gaming", "DMG%": "23.1%", "CSPM": "6.5", "XPD10": "111", "CS%P15": "22.9%"}, "/LEC_2021_Summer_Playoffs": {"KDA": "2.2", "D": "44", "DPM": "452", "Pos": "Top", "CTR%": "36%", "W%": "27%", "GD10": "-78", "KP": "61.0%", "DTH%": "22.6%", "CSD10": "4.2", "A": "65", "WPM": "0.38", "EGPM": "238", "GOLD%": "21.3%", "WCPM": "0.16", "KS%": "20.1%", "K": "32", "GP": "11", "FB%": "9%", "Team": "Rogue", "DMG%": "23.4%", "CSPM": "7.1", "XPD10": "266", "CS%P15": "22.4%"}, "/LEC_2020_Spring_Playoffs": {"KDA": "3", "D": "46", "DPM": "364", "Pos": "Top", "CTR%": "56%", "W%": "44%", "GD10": "-1", "KP": "67.2%", "DTH%": "22.0%", "CSD10": "6.4", "A": "110", "WPM": "0.43", "EGPM": "227", "GOLD%": "21.7%", "WCPM": "0.18", "KS%": "13.2%", "K": "27", "GP": "18", "FB%": "39%", "Team": "FC Schalke 04 Esports", "DMG%": "20.4%", "CSPM": "7.6", "XPD10": "67", "CS%P15": "23.1%"}, "/LEC_2017_Summer_Playoffs": {"KDA": "1.5", "D": "24", "DPM": "388", "Pos": "Top", "CTR%": "", "W%": "25%", "GD10": "135", "KP": "63.2%", "DTH%": "22.6%", "CSD10": "1.6", "A": "18", "WPM": "0.46", "EGPM": "223", "GOLD%": "21.5%", "WCPM": "0.1", "KS%": "31.6%", "K": "18", "GP": "8", "FB%": "25%", "Team": "H2k-Gaming", "DMG%": "22.4%", "CSPM": "7.7", "XPD10": "208", "CS%P15": "21.8%"}, "/LEC_2020_Summer_RegularSeason": {"KDA": "3", "D": "46", "DPM": "364", "Pos": "Top", "CTR%": "56%", "W%": "44%", "GD10": "-1", "KP": "67.2%", "DTH%": "22.0%", "CSD10": "6.4", "A": "110", "WPM": "0.43", "EGPM": "227", "GOLD%": "21.7%", "WCPM": "0.18", "KS%": "13.2%", "K": "27", "GP": "18", "FB%": "39%", "Team": "FC Schalke 04 Esports", "DMG%": "20.4%", "CSPM": "7.6", "XPD10": "67", "CS%P15": "23.1%"}, "/LEC_2018_Spring_Playoffs": {"KDA": "2.2", "D": "33", "DPM": "391", "Pos": "Top", "CTR%": "50%", "W%": "58%", "GD10": "-32", "KP": "60.8%", "DTH%": "33.3%", "CSD10": "-3.4", "A": "51", "WPM": "0.53", "EGPM": "227", "GOLD%": "20.6%", "WCPM": "0.23", "KS%": "18.3%", "K": "22", "GP": "12", "FB%": "33%", "Team": "Splyce", "DMG%": "23.0%", "CSPM": "7.9", "XPD10": "47", "CS%P15": "21.8%"}, "/LEC_2017_Spring_Playoffs": {"KDA": "0.4", "D": "14", "DPM": "299", "Pos": "Top", "CTR%": "", "W%": "0%", "GD10": "-138", "KP": "30.0%", "DTH%": "23.7%", "CSD10": "0.3", "A": "5", "WPM": "0.39", "EGPM": "186", "GOLD%": "20.4%", "WCPM": "0.16", "KS%": "5.0%", "K": "1", "GP": "3", "FB%": "0%", "Team": "H2k-Gaming", "DMG%": "18.0%", "CSPM": "7.5", "XPD10": "265", "CS%P15": "24.7%"}, "/LEC_2017_Spring_RegularSeason": {"KDA": "4.6", "D": "37", "DPM": "371", "Pos": "Top", "CTR%": "", "W%": "78%", "GD10": "-21", "KP": "69.6%", "DTH%": "25.0%", "CSD10": "-4.1", "A": "123", "WPM": "0.45", "EGPM": "249", "GOLD%": "20.8%", "WCPM": "0.13", "KS%": "19.8%", "K": "49", "GP": "18", "FB%": "33%", "Team": "H2k-Gaming", "DMG%": "18.0%", "CSPM": "7.2", "XPD10": "-40", "CS%P15": "24.4%"}, "/LEC_2019_Spring_Playoffs": {"KDA": "2.7", "D": "57", "DPM": "387", "Pos": "Top", "CTR%": "44%", "W%": "61%", "GD10": "-159", "KP": "55.6%", "DTH%": "29.2%", "CSD10": "-4.2", "A": "121", "WPM": "0.46", "EGPM": "232", "GOLD%": "19.7%", "WCPM": "0.16", "KS%": "11.6%", "K": "32", "GP": "18", "FB%": "11%", "Team": "FC Schalke 04 Esports", "DMG%": "20.5%", "CSPM": "7.4", "XPD10": "-202", "CS%P15": "21.4%"}, "/LEC_2015_Spring_RegularSeason": {"KDA": "4.3", "D": "41", "DPM": "415", "Pos": "Top", "CTR%": "", "W%": "67%", "GD10": "44", "KP": "69.7%", "DTH%": "19.9%", "CSD10": "2.8", "A": "135", "WPM": "0.41", "EGPM": "215", "GOLD%": "20.6%", "WCPM": "0.08", "KS%": "15.9%", "K": "40", "GP": "18", "FB%": "33%", "Team": "H2k-Gaming", "DMG%": "23.1%", "CSPM": "6.5", "XPD10": "111", "CS%P15": "22.9%"}, "/LEC_2016_Spring_RegularSeason": {"KDA": "4.6", "D": "37", "DPM": "371", "Pos": "Top", "CTR%": "", "W%": "78%", "GD10": "-21", "KP": "69.6%", "DTH%": "25.0%", "CSD10": "-4.1", "A": "123", "WPM": "0.45", "EGPM": "249", "GOLD%": "20.8%", "WCPM": "0.13", "KS%": "19.8%", "K": "49", "GP": "18", "FB%": "33%", "Team": "H2k-Gaming", "DMG%": "18.0%", "CSPM": "7.2", "XPD10": "-40", "CS%P15": "24.4%"}, "/LEC_2019_Summer_Playoffs": {"KDA": "3", "D": "34", "DPM": "435", "Pos": "Top", "CTR%": "73%", "W%": "55%", "GD10": "-79", "KP": "53.2%", "DTH%": "23.4%", "CSD10": "-6.2", "A": "64", "WPM": "0.44", "EGPM": "235", "GOLD%": "20.3%", "WCPM": "0.15", "KS%": "19.5%", "K": "37", "GP": "11", "FB%": "45%", "Team": "FC Schalke 04 Esports", "DMG%": "23.4%", "CSPM": "7.1", "XPD10": "-244", "CS%P15": "21.6%"}, "/LEC_2018_Summer_Playoffs": {"KDA": "2", "D": "17", "DPM": "425", "Pos": "Top", "CTR%": "0%", "W%": "40%", "GD10": "-246", "KP": "58.6%", "DTH%": "37.8%", "CSD10": "-10", "A": "28", "WPM": "0.48", "EGPM": "230", "GOLD%": "20.9%", "WCPM": "0.26", "KS%": "10.3%", "K": "6", "GP": "5", "FB%": "0%", "Team": "Splyce", "DMG%": "23.3%", "CSPM": "8.3", "XPD10": "14", "CS%P15": "24.2%"}, "/LEC_2021_Spring_RegularSeason": {"KDA": "2.4", "D": "53", "DPM": "346", "Pos": "Top", "CTR%": "47%", "W%": "53%", "GD10": "39", "KP": "56.6%", "DTH%": "23.6%", "CSD10": "3.9", "A": "100", "WPM": "0.42", "EGPM": "220", "GOLD%": "19.3%", "WCPM": "0.19", "KS%": "12.7%", "K": "29", "GP": "17", "FB%": "18%", "Team": "Rogue", "DMG%": "18.3%", "CSPM": "7.2", "XPD10": "80", "CS%P15": "20.6%"}, "/LEC_2020_Summer_Playoffs": {"KDA": "3.8", "D": "15", "DPM": "411", "Pos": "Top", "CTR%": "57%", "W%": "57%", "GD10": "290", "KP": "58.2%", "DTH%": "17.0%", "CSD10": "7.4", "A": "37", "WPM": "0.4", "EGPM": "253", "GOLD%": "22.2%", "WCPM": "0.13", "KS%": "20.4%", "K": "20", "GP": "7", "FB%": "29%", "Team": "FC Schalke 04 Esports", "DMG%": "23.5%", "CSPM": "7.4", "XPD10": "62", "CS%P15": "23.9%"}, "/LEC_2021_Spring_Playoffs": {"KDA": "4", "D": "39", "DPM": "461", "Pos": "Top", "CTR%": "61%", "W%": "72%", "GD10": "274", "KP": "55.6%", "DTH%": "20.5%", "CSD10": "2.4", "A": "104", "WPM": "0.4", "EGPM": "253", "GOLD%": "20.4%", "WCPM": "0.22", "KS%": "18.3%", "K": "51", "GP": "18", "FB%": "22%", "Team": "Rogue", "DMG%": "23.6%", "CSPM": "7.6", "XPD10": "89", "CS%P15": "22.2%"}, "/LEC_2018_Spring_RegularSeason": {"KDA": "2.2", "D": "33", "DPM": "391", "Pos": "Top", "CTR%": "50%", "W%": "58%", "GD10": "-32", "KP": "60.8%", "DTH%": "33.3%", "CSD10": "-3.4", "A": "51", "WPM": "0.53", "EGPM": "227", "GOLD%": "20.6%", "WCPM": "0.23", "KS%": "18.3%", "K": "22", "GP": "12", "FB%": "33%", "Team": "Splyce", "DMG%": "23.0%", "CSPM": "7.9", "XPD10": "47", "CS%P15": "21.8%"}, "/LEC_2015_Spring_Playoffs": {"KDA": "4.3", "D": "41", "DPM": "415", "Pos": "Top", "CTR%": "", "W%": "67%", "GD10": "44", "KP": "69.7%", "DTH%": "19.9%", "CSD10": "2.8", "A": "135", "WPM": "0.41", "EGPM": "215", "GOLD%": "20.6%", "WCPM": "0.08", "KS%": "15.9%", "K": "40", "GP": "18", "FB%": "33%", "Team": "H2k-Gaming", "DMG%": "23.1%", "CSPM": "6.5", "XPD10": "111", "CS%P15": "22.9%"}, "/LEC_2019_Summer_RegularSeason": {"KDA": "3.3", "D": "38", "DPM": "413", "Pos": "Top", "CTR%": "44%", "W%": "33%", "GD10": "-15", "KP": "56.6%", "DTH%": "16.8%", "CSD10": "1.8", "A": "80", "WPM": "0.4", "EGPM": "243", "GOLD%": "22.7%", "WCPM": "0.2", "KS%": "20.4%", "K": "45", "GP": "18", "FB%": "17%", "Team": "FC Schalke 04 Esports", "DMG%": "22.1%", "CSPM": "7.9", "XPD10": "66", "CS%P15": "23.5%"}, "/LEC_2018_Summer_RegularSeason": {"KDA": "2.1", "D": "47", "DPM": "463", "Pos": "Top", "CTR%": "47%", "W%": "47%", "GD10": "168", "KP": "51.1%", "DTH%": "24.0%", "CSD10": "3.4", "A": "51", "WPM": "0.45", "EGPM": "263", "GOLD%": "22.7%", "WCPM": "0.2", "KS%": "24.2%", "K": "46", "GP": "19", "FB%": "0%", "Team": "FC Schalke 04 Esports", "DMG%": "27.4%", "CSPM": "8.3", "XPD10": "6", "CS%P15": "23.2%"}}