{"/LEC_2018_Spring_Playoffs": {"KDA": "0.9", "D": "7", "DPM": "263", "Pos": "Top", "CTR%": "67%", "W%": "0%", "GD10": "-270", "KP": "50.0%", "DTH%": "16.3%", "CSD10": "-6.3", "A": "3", "WPM": "0.54", "EGPM": "197", "GOLD%": "22.1%", "WCPM": "0.08", "KS%": "25.0%", "K": "3", "GP": "3", "FB%": "0%", "Team": "Team ROCCAT", "DMG%": "22.3%", "CSPM": "8.4", "XPD10": "-267", "CS%P15": "24.8%"}, "/LEC_2019_Spring_Playoffs": {"KDA": "3.2", "D": "24", "DPM": "325", "Pos": "Top", "CTR%": "17%", "W%": "33%", "GD10": "-109", "KP": "56.2%", "DTH%": "17.6%", "CSD10": "-4", "A": "54", "WPM": "0.44", "EGPM": "220", "GOLD%": "20.8%", "WCPM": "0.15", "KS%": "16.8%", "K": "23", "GP": "12", "FB%": "33%", "Team": "Rogue", "DMG%": "20.7%", "CSPM": "7.5", "XPD10": "29", "CS%P15": "24.2%"}, "/LEC_2018_Spring_RegularSeason": {"KDA": "0.9", "D": "7", "DPM": "263", "Pos": "Top", "CTR%": "67%", "W%": "0%", "GD10": "-270", "KP": "50.0%", "DTH%": "16.3%", "CSD10": "-6.3", "A": "3", "WPM": "0.54", "EGPM": "197", "GOLD%": "22.1%", "WCPM": "0.08", "KS%": "25.0%", "K": "3", "GP": "3", "FB%": "0%", "Team": "Team ROCCAT", "DMG%": "22.3%", "CSPM": "8.4", "XPD10": "-267", "CS%P15": "24.8%"}, "/LEC_2018_Summer_RegularSeason": {"KDA": "1.6", "D": "38", "DPM": "320", "Pos": "Top", "CTR%": "50%", "W%": "0%", "GD10": "-75", "KP": "64.6%", "DTH%": "21.3%", "CSD10": "0.9", "A": "42", "WPM": "0.39", "EGPM": "220", "GOLD%": "22.5%", "WCPM": "0.12", "KS%": "20.8%", "K": "20", "GP": "12", "FB%": "25%", "Team": "Rogue", "DMG%": "23.0%", "CSPM": "7.9", "XPD10": "22", "CS%P15": "25.2%"}}