{"/LCK_2020_Spring_RegularSeason": {"KDA": "2.6", "D": "120", "DPM": "233", "Pos": "Jungle", "CTR%": "64%", "W%": "38%", "STL": "", "GD10": "25", "KP": "75.0%", "DTH%": "20.7%", "CSD10": "0.7", "A": "228", "WPM": "0.67", "EGPM": "188", "GOLD%": "18.8%", "WCPM": "0.45", "KS%": "20.7%", "K": "87", "GP": "45", "FB%": "33%", "D%P15": "", "Team": "Hanwha Life Esports", "DMG%": "13.6%", "CSPM": "5.6", "XPD10": "78", "CS%P15": "16.7%"}, "/LCK_2017_Summer_RegularSeason": {"KDA": "2.4", "D": "13", "DPM": "229", "Pos": "Jungle", "CTR%": "29%", "W%": "57%", "STL": "", "GD10": "197", "KP": "57.4%", "DTH%": "21.0%", "CSD10": "4.9", "A": "17", "WPM": "0.96", "EGPM": "210", "GOLD%": "17.9%", "WCPM": "0.45", "KS%": "25.9%", "K": "14", "GP": "7", "FB%": "29%", "D%P15": "", "Team": "Samsung Galaxy", "DMG%": "15.3%", "CSPM": "5", "XPD10": "117", "CS%P15": "14.0%"}, "/LCK_2017_Spring_Playoffs": {"KDA": "1.2", "D": "6", "DPM": "216", "Pos": "Jungle", "CTR%": "0%", "W%": "0%", "STL": "", "GD10": "-167", "KP": "53.8%", "DTH%": "17.6%", "CSD10": "3.5", "A": "3", "WPM": "0.72", "EGPM": "196", "GOLD%": "21.9%", "WCPM": "0.29", "KS%": "30.8%", "K": "4", "GP": "2", "FB%": "0%", "D%P15": "", "Team": "Samsung Galaxy", "DMG%": "14.2%", "CSPM": "5.5", "XPD10": "525", "CS%P15": "16.8%"}, "/LCK_2018_Spring_RegularSeason": {"KDA": "2", "D": "39", "DPM": "187", "Pos": "Jungle", "CTR%": "41%", "W%": "47%", "STL": "", "GD10": "165", "KP": "69.6%", "DTH%": "21.5%", "CSD10": "5.2", "A": "52", "WPM": "1.32", "EGPM": "206", "GOLD%": "18.0%", "WCPM": "0.55", "KS%": "23.2%", "K": "26", "GP": "17", "FB%": "24%", "D%P15": "", "Team": "KSV eSports", "DMG%": "10.5%", "CSPM": "6.1", "XPD10": "141", "CS%P15": "15.4%"}, "/LCK_2020_Summer_RegularSeason": {"KDA": "1.5", "D": "51", "DPM": "213", "Pos": "Jungle", "CTR%": "75%", "W%": "19%", "STL": "", "GD10": "-57", "KP": "64.2%", "DTH%": "23.8%", "CSD10": "-2.9", "A": "54", "WPM": "0.67", "EGPM": "168", "GOLD%": "17.6%", "WCPM": "0.41", "KS%": "20.3%", "K": "25", "GP": "16", "FB%": "13%", "D%P15": "", "Team": "Hanwha Life Esports", "DMG%": "13.7%", "CSPM": "5.2", "XPD10": "10", "CS%P15": "14.3%"}, "/LCK_2018_Summer_RegularSeason": {"KDA": "3.3", "D": "37", "DPM": "246", "Pos": "Jungle", "CTR%": "56%", "W%": "67%", "STL": "", "GD10": "237", "KP": "68.3%", "DTH%": "26.4%", "CSD10": "9", "A": "77", "WPM": "0.41", "EGPM": "231", "GOLD%": "19.3%", "WCPM": "0.44", "KS%": "25.6%", "K": "46", "GP": "18", "FB%": "39%", "D%P15": "", "Team": "Gen.G", "DMG%": "14.1%", "CSPM": "6.1", "XPD10": "305", "CS%P15": "17.3%"}, "/LCK_2017_Summer_Playoffs": {"KDA": "2.3", "D": "4", "DPM": "90", "Pos": "Jungle", "CTR%": "50%", "W%": "0%", "STL": "", "GD10": "24", "KP": "100.0%", "DTH%": "16.7%", "CSD10": "0", "A": "9", "WPM": "0.92", "EGPM": "169", "GOLD%": "16.4%", "WCPM": "0.3", "KS%": "0.0%", "K": "0", "GP": "2", "FB%": "50%", "D%P15": "", "Team": "Samsung Galaxy", "DMG%": "6.5%", "CSPM": "4.1", "XPD10": "-245", "CS%P15": "11.6%"}, "/LCK_2016_Summer_RegularSeason": {"KDA": "2.3", "D": "127", "DPM": "306", "Pos": "Jungle", "CTR%": "", "W%": "28%", "STL": "", "GD10": "10", "KP": "73.8%", "DTH%": "24.9%", "CSD10": "0.8", "A": "182", "WPM": "0.74", "EGPM": "216", "GOLD%": "20.2%", "WCPM": "0.43", "KS%": "27.0%", "K": "105", "GP": "43", "FB%": "37%", "D%P15": "", "Team": "CJ Entus", "DMG%": "17.4%", "CSPM": "4.4", "XPD10": "-45", "CS%P15": "13.9%"}, "/LCK_2017_Spring_RegularSeason": {"KDA": "4.2", "D": "57", "DPM": "305", "Pos": "Jungle", "CTR%": "47%", "W%": "77%", "STL": "", "GD10": "250", "KP": "68.5%", "DTH%": "23.1%", "CSD10": "2", "A": "132", "WPM": "0.75", "EGPM": "258", "GOLD%": "20.8%", "WCPM": "0.36", "KS%": "31.0%", "K": "109", "GP": "30", "FB%": "60%", "D%P15": "", "Team": "Samsung Galaxy", "DMG%": "16.1%", "CSPM": "5.9", "XPD10": "223", "CS%P15": "18.3%"}}