{"/LCK_2018_Spring_RegularSeason": {"KDA": "5", "D": "3", "DPM": "114", "Pos": "Jungle", "CTR%": "50%", "W%": "100%", "STL": "", "GD10": "220", "KP": "60.0%", "DTH%": "42.9%", "CSD10": "4.5", "A": "14", "WPM": "0.68", "EGPM": "185", "GOLD%": "13.2%", "WCPM": "0.56", "KS%": "4.0%", "K": "1", "GP": "2", "FB%": "0%", "D%P15": "", "Team": "KT Rolster", "DMG%": "5.4%", "CSPM": "4.9", "XPD10": "63", "CS%P15": "9.3%"}, "/LCK_2018_Summer_RegularSeason": {"KDA": "1.9", "D": "23", "DPM": "225", "Pos": "Jungle", "CTR%": "43%", "W%": "57%", "STL": "", "GD10": "5", "KP": "61.1%", "DTH%": "31.9%", "CSD10": "-5", "A": "30", "WPM": "0.33", "EGPM": "206", "GOLD%": "17.8%", "WCPM": "0.45", "KS%": "19.4%", "K": "14", "GP": "7", "FB%": "57%", "D%P15": "", "Team": "KT Rolster", "DMG%": "13.8%", "CSPM": "5.5", "XPD10": "-66", "CS%P15": "15.1%"}, "/LCK_2018_Spring_Playoffs": {"KDA": "2.3", "D": "4", "DPM": "149", "Pos": "Jungle", "CTR%": "0%", "W%": "33%", "STL": "", "GD10": "322", "KP": "60.0%", "DTH%": "17.4%", "CSD10": "11.3", "A": "6", "WPM": "1.05", "EGPM": "195", "GOLD%": "17.1%", "WCPM": "0.58", "KS%": "20.0%", "K": "3", "GP": "3", "FB%": "33%", "D%P15": "", "Team": "KT Rolster", "DMG%": "10.0%", "CSPM": "5.8", "XPD10": "631", "CS%P15": "12.3%"}}