{"/LCK_2015_Spring_Playoffs": {"KDA": "2.7", "D": "16", "DPM": "199", "Pos": "Jungle", "CTR%": "", "W%": "60%", "STL": "", "GD10": "160", "KP": "67.2%", "DTH%": "28.1%", "CSD10": "5", "A": "32", "WPM": "0.96", "EGPM": "189", "GOLD%": "17.9%", "WCPM": "0.37", "KS%": "17.2%", "K": "11", "GP": "5", "FB%": "40%", "D%P15": "", "Team": "SK Telecom T1", "DMG%": "10.8%", "CSPM": "3.4", "XPD10": "37", "CS%P15": "11.1%"}, "/LCK_2015_Summer_RegularSeason": {"KDA": "3.7", "D": "14", "DPM": "170", "Pos": "Jungle", "CTR%": "", "W%": "100%", "STL": "", "GD10": "-79", "KP": "60.5%", "DTH%": "27.5%", "CSD10": "-2.2", "A": "46", "WPM": "1.06", "EGPM": "170", "GOLD%": "15.5%", "WCPM": "0.41", "KS%": "7.0%", "K": "6", "GP": "6", "FB%": "50%", "D%P15": "", "Team": "SK Telecom T1", "DMG%": "8.2%", "CSPM": "3.1", "XPD10": "-254", "CS%P15": "9.5%"}, "/LCK_2015_Spring_RegularSeason": {"KDA": "8.1", "D": "8", "DPM": "163", "Pos": "Jungle", "CTR%": "", "W%": "100%", "STL": "", "GD10": "467", "KP": "65.0%", "DTH%": "25.0%", "CSD10": "4.3", "A": "52", "WPM": "0.83", "EGPM": "206", "GOLD%": "16.5%", "WCPM": "0.42", "KS%": "13.0%", "K": "13", "GP": "6", "FB%": "67%", "D%P15": "", "Team": "SK Telecom T1", "DMG%": "8.3%", "CSPM": "3.2", "XPD10": "307", "CS%P15": "9.1%"}}