{"/LCK_2021_Spring_Playoffs": {"KDA": "2.1", "D": "15", "DPM": "244", "Pos": "Jungle", "CTR%": "60%", "W%": "40%", "STL": "", "GD10": "-228", "KP": "54.4%", "DTH%": "20.8%", "CSD10": "-2.6", "A": "23", "WPM": "0.34", "EGPM": "173", "GOLD%": "16.5%", "WCPM": "0.46", "KS%": "14.0%", "K": "8", "GP": "5", "FB%": "40%", "D%P15": "", "Team": "Hanwha Life Esports", "DMG%": "11.2%", "CSPM": "5.6", "XPD10": "-303", "CS%P15": "14.6%"}, "/LCK_2021_Spring_RegularSeason": {"KDA": "3.1", "D": "44", "DPM": "329", "Pos": "Jungle", "CTR%": "47%", "W%": "71%", "STL": "", "GD10": "-69", "KP": "63.3%", "DTH%": "23.2%", "CSD10": "-0.4", "A": "87", "WPM": "0.3", "EGPM": "217", "GOLD%": "18.6%", "WCPM": "0.48", "KS%": "22.8%", "K": "49", "GP": "17", "FB%": "24%", "D%P15": "", "Team": "Hanwha Life Esports", "DMG%": "14.9%", "CSPM": "6.5", "XPD10": "-56", "CS%P15": "17.7%"}, "/LCK_2021_Summer_RegularSeason": {"KDA": "2.1", "D": "47", "DPM": "432", "Pos": "Jungle", "CTR%": "9%", "W%": "18%", "STL": "", "GD10": "-93", "KP": "79.0%", "DTH%": "25.3%", "CSD10": "5.2", "A": "61", "WPM": "0.37", "EGPM": "198", "GOLD%": "19.1%", "WCPM": "0.23", "KS%": "29.8%", "K": "37", "GP": "11", "FB%": "18%", "D%P15": "", "Team": "Hanwha Life Esports", "DMG%": "22.2%", "CSPM": "5.3", "XPD10": "24", "CS%P15": "14.2%"}}