{"/LCK_2013_Summer_RegularSeason": {"KDA": "4.5", "D": "13", "DPM": "", "Pos": "ADC", "CTR%": "", "W%": "43%", "STL": "", "GD10": "", "KP": "62.4%", "DTH%": "13.7%", "CSD10": "", "A": "28", "WPM": "", "EGPM": "221", "GOLD%": "26.5%", "WCPM": "", "KS%": "32.3%", "K": "30", "GP": "7", "FB%": "", "D%P15": "", "Team": "NaJin White Shield", "DMG%": "", "CSPM": "", "XPD10": "", "CS%P15": ""}, "/LCK_2015_Spring_RegularSeason": {"KDA": "4.3", "D": "12", "DPM": "389", "Pos": "ADC", "CTR%": "", "W%": "33%", "STL": "", "GD10": "33", "KP": "70.3%", "DTH%": "13.5%", "CSD10": "1.5", "A": "33", "WPM": "0.16", "EGPM": "252", "GOLD%": "26.9%", "WCPM": "0.23", "KS%": "25.7%", "K": "19", "GP": "6", "FB%": "0%", "D%P15": "", "Team": "NaJin e-mFire", "DMG%": "27.7%", "CSPM": "8.7", "XPD10": "73", "CS%P15": "31.9%"}, "/LCK_2014_Spring_RegularSeason": {"KDA": "3.9", "D": "47", "DPM": "", "Pos": "ADC", "CTR%": "", "W%": "62%", "STL": "", "GD10": "", "KP": "64.4%", "DTH%": "18.0%", "CSD10": "", "A": "108", "WPM": "", "EGPM": "279", "GOLD%": "25.9%", "WCPM": "", "KS%": "26.4%", "K": "75", "GP": "21", "FB%": "", "D%P15": "", "Team": "NaJin White Shield", "DMG%": "", "CSPM": "", "XPD10": "", "CS%P15": ""}, "/LCK_2014_Winter_RegularSeason": {"KDA": "3.6", "D": "51", "DPM": "", "Pos": "ADC", "CTR%": "", "W%": "53%", "STL": "", "GD10": "", "KP": "68.0%", "DTH%": "17.5%", "CSD10": "", "A": "111", "WPM": "", "EGPM": "244", "GOLD%": "24.7%", "WCPM": "", "KS%": "26.8%", "K": "72", "GP": "19", "FB%": "", "D%P15": "", "Team": "NaJin White Shield", "DMG%": "", "CSPM": "", "XPD10": "", "CS%P15": ""}, "/LCK_2014_Summer_RegularSeason": {"KDA": "3.5", "D": "30", "DPM": "", "Pos": "ADC", "CTR%": "", "W%": "45%", "STL": "", "GD10": "", "KP": "71.4%", "DTH%": "19.2%", "CSD10": "", "A": "70", "WPM": "", "EGPM": "248", "GOLD%": "23.5%", "WCPM": "", "KS%": "23.8%", "K": "35", "GP": "11", "FB%": "", "D%P15": "", "Team": "NaJin White Shield", "DMG%": "", "CSPM": "", "XPD10": "", "CS%P15": ""}}