{"/LEC_2021_Summer_RegularSeason": {"KP": "72.7%", "K": "11", "DMG%": "7.5%", "Pos": "Support", "W%": "44%", "CSPM": "1.1", "DTH%": "25.7%", "A": "170", "EGPM": "101", "WPM": "1.42", "GD10": "60", "DPM": "144", "FB%": "22%", "KS%": "4.4%", "CSD10": "-1", "D": "65", "KDA": "2.8", "WCPM": "0.32", "GP": "18", "CS%P15": "2.4%", "XPD10": "5", "Team": "Team Vitality", "CTR%": "39%", "GOLD%": "8.7%"}, "/LEC_2021_Summer_Playoffs": {"KP": "58.6%", "K": "1", "DMG%": "7.5%", "Pos": "Support", "W%": "40%", "CSPM": "1", "DTH%": "24.7%", "A": "33", "EGPM": "89", "WPM": "1.28", "GD10": "-169", "DPM": "168", "FB%": "0%", "KS%": "1.7%", "CSD10": "-1.6", "D": "19", "KDA": "1.8", "WCPM": "0.32", "GP": "5", "CS%P15": "2.2%", "XPD10": "-477", "Team": "Team Vitality", "CTR%": "40%", "GOLD%": "7.8%"}, "/LEC_2020_Spring_Playoffs": {"KP": "80.3%", "K": "7", "DMG%": "7.3%", "Pos": "Support", "W%": "39%", "CSPM": "1", "DTH%": "21.9%", "A": "148", "EGPM": "92", "WPM": "1.73", "GD10": "-4", "DPM": "124", "FB%": "33%", "KS%": "3.6%", "CSD10": "0.8", "D": "47", "KDA": "3.3", "WCPM": "0.37", "GP": "18", "CS%P15": "2.7%", "XPD10": "-174", "Team": "Team Vitality", "CTR%": "44%", "GOLD%": "8.5%"}, "/LEC_2020_Summer_RegularSeason": {"KP": "80.3%", "K": "7", "DMG%": "7.3%", "Pos": "Support", "W%": "39%", "CSPM": "1", "DTH%": "21.9%", "A": "148", "EGPM": "92", "WPM": "1.73", "GD10": "-4", "DPM": "124", "FB%": "33%", "KS%": "3.6%", "CSD10": "0.8", "D": "47", "KDA": "3.3", "WCPM": "0.37", "GP": "18", "CS%P15": "2.7%", "XPD10": "-174", "Team": "Team Vitality", "CTR%": "44%", "GOLD%": "8.5%"}, "/LEC_2021_Spring_Playoffs": {"KP": "72.7%", "K": "11", "DMG%": "7.5%", "Pos": "Support", "W%": "44%", "CSPM": "1.1", "DTH%": "25.7%", "A": "170", "EGPM": "101", "WPM": "1.42", "GD10": "60", "DPM": "144", "FB%": "22%", "KS%": "4.4%", "CSD10": "-1", "D": "65", "KDA": "2.8", "WCPM": "0.32", "GP": "18", "CS%P15": "2.4%", "XPD10": "5", "Team": "Team Vitality", "CTR%": "39%", "GOLD%": "8.7%"}}